tj_kits_fire/__init__.py
tj_kits_fire/tj_kits.py
tj_kits_fire-0.0.6.dist-info/METADATA
tj_kits_fire-0.0.6.dist-info/WHEEL
tj_kits_fire-0.0.6.dist-info/top_level.txt
tj_kits_fire-0.0.6.dist-info/RECORD
